{"lang":"ja","stage":3,"title":"short, easy phrases","sentences":[{"t":"時間見てよ。","en":"Look at the time.","r":"Jikan mite yo.","a":"n_356438292b94.mp3"},{"t":"そう思うよ。","en":"I think so.","r":"Sō omou yo.","a":"n_49cce93b621b.mp3"},{"t":"今日はうれしいんだ。","en":"Today I'm happy.","r":"Kyō wa ureshii n da.","a":"n_1ad64a7d6cbe.mp3"},{"t":"彼女うれしそう。","en":"She's happy.","r":"Kanojo ureshisō.","a":"n_1b08b75197c4.mp3"},{"t":"お金ないんだ。","en":"I don't have any money.","r":"Okane nai n da.","a":"n_92e22d7665ff.mp3"},{"t":"寝なきゃだめだよ。","en":"You've got to sleep.","r":"Nenakya dame da yo.","a":"n_478232c7354a.mp3"},{"t":"どこ行くの？","en":"Where are you going?","r":"Doko iku no?","a":"n_3bbe2443104b.mp3"},{"t":"昨日いっぱいやったよ。","en":"I did a lot yesterday.","r":"Kinō ippai yatta yo.","a":"n_9ecefcd23905.mp3"},{"t":"ご飯作ったよ。","en":"I made the food.","r":"Gohan tsukutta yo.","a":"n_74ee8532606d.mp3"},{"t":"家にいたよ。","en":"I was at home.","r":"Ie ni ita yo.","a":"n_89314f0de8c7.mp3"},{"t":"すごく疲れてたんだ。","en":"I was very tired.","r":"Sugoku tsukareteta n da.","a":"n_484699bb94a4.mp3"},{"t":"医者がいる。","en":"I need a doctor.","r":"Isha ga iru.","a":"n_e1325600f65c.mp3"},{"t":"家にいる？","en":"Are you home?","r":"Ie ni iru?","a":"n_3c26fe83cde2.mp3"},{"t":"天気が悪いね。","en":"The weather is bad.","r":"Tenki ga warui ne.","a":"n_d152b174ded9.mp3"},{"t":"具合が悪い。","en":"I feel bad.","r":"Guai ga warui.","a":"n_aa1636bf7574.mp3"},{"t":"なにも見えない。","en":"I can't see anything.","r":"Nani mo mienai.","a":"n_6c8cccd84525.mp3"},{"t":"早く起きるよ。","en":"I get up early.","r":"Hayaku okiru yo.","a":"n_151f93232580.mp3"},{"t":"こちらアナだよ。","en":"This is Ana.","r":"Kochira Ana da yo.","a":"n_d8a08304f12e.mp3"},{"t":"まだ準備できてない。","en":"I'm not ready.","r":"Mada junbi dekitenai.","a":"n_3ce336c822ba.mp3"},{"t":"二つ買いたい。","en":"I want to buy two.","r":"Futatsu kaitai.","a":"n_1e44e074cc70.mp3"},{"t":"水を買いたい。","en":"I want to buy water.","r":"Mizu o kaitai.","a":"n_08121b163d69.mp3"},{"t":"もっと寝たほうがいいよ。","en":"You should sleep more.","r":"Motto neta hō ga ii yo.","a":"n_cb38f4b3f1c3.mp3"},{"t":"遠くないよ。","en":"It's not far.","r":"Tōku nai yo.","a":"n_f1bcf28fc9b7.mp3"},{"t":"電車で行くよ。","en":"We're going by train.","r":"Densha de iku yo.","a":"n_f6f7cb5a6d87.mp3"},{"t":"それ安いね。","en":"That's cheap.","r":"Sore yasui ne.","a":"n_33fb072195f8.mp3"},{"t":"こちらカルロスだよ。","en":"This is Carlos.","r":"Kochira Karurosu da yo.","a":"n_9228e5375959.mp3"},{"t":"まだ早いよ。","en":"It's still early.","r":"Mada hayai yo.","a":"n_33f4a82aaea6.mp3"},{"t":"どうしたの？","en":"What's wrong with you?","r":"Dō shita no?","a":"n_6f4d76f8a97b.mp3"},{"t":"彼どうしたの？","en":"What's wrong with him?","r":"Kare dō shita no?","a":"n_0aee549e6db7.mp3"},{"t":"なにが起きてるか知ってる？","en":"Do you know what's going on?","r":"Nani ga okiteru ka shitteru?","a":"n_f5997c8704d0.mp3"},{"t":"寝るの大好き。","en":"I love sleeping.","r":"Neru no daisuki.","a":"n_07416be2d4df.mp3"},{"t":"いつかわかんない。","en":"I don't know when.","r":"Itsu ka wakannai.","a":"n_a93a16f21c01.mp3"},{"t":"ベッドを整えるよ。","en":"I make my bed.","r":"Beddo o totonoeru yo.","a":"n_8afc26011d49.mp3"},{"t":"寝るの遅いんだ。","en":"I go to bed late.","r":"Neru no osoi n da.","a":"n_2690622d0e00.mp3"},{"t":"街に行くよ。","en":"I'm going downtown.","r":"Machi ni iku yo.","a":"n_6777fe3c126e.mp3"},{"t":"すごく高いね。","en":"It's very expensive.","r":"Sugoku takai ne.","a":"n_24b766cf712a.mp3"},{"t":"今日は悲しいんだ。","en":"Today I'm sad.","r":"Kyō wa kanashii n da.","a":"n_3266d77912fb.mp3"},{"t":"彼悲しそう。","en":"He's sad.","r":"Kare kanashisō.","a":"n_5ce6bd11c4ea.mp3"},{"t":"今日は暑いね。","en":"It's hot today.","r":"Kyō wa atsui ne.","a":"n_956e1a894b43.mp3"},{"t":"できるよ。","en":"I can do it.","r":"Dekiru yo.","a":"n_d2ea3e5f5d3d.mp3"},{"t":"できる？","en":"Can you do it?","r":"Dekiru?","a":"n_033c908ab768.mp3"},{"t":"質問したよ。","en":"I asked a question.","r":"Shitsumon shita yo.","a":"n_f090e07cef1b.mp3"},{"t":"どういう意味？","en":"What do you mean?","r":"Dō iu imi?","a":"n_f604c7d3a90d.mp3"},{"t":"明日払えるよ。","en":"I can pay tomorrow.","r":"Ashita haraeru yo.","a":"n_30ed2b2b0210.mp3"},{"t":"タクシーで行くの？","en":"Are you going by taxi?","r":"Takushī de iku no?","a":"n_da81c9185e33.mp3"},{"t":"アナっていうんだ。","en":"My name is Ana.","r":"Ana tte iu n da.","a":"n_381f477aa531.mp3"},{"t":"彼、名前なんていうの？","en":"What's his name?","r":"Kare, namae nan te iu no?","a":"n_e74037314785.mp3"},{"t":"カルロスっていうんだ。","en":"His name is Carlos.","r":"Karurosu tte iu n da.","a":"n_b0acd444f313.mp3"},{"t":"犬を飼ってるよ。","en":"I have a dog.","r":"Inu o katteru yo.","a":"n_4f8a97ebfb7f.mp3"},{"t":"ちょっといい？","en":"Do you have a minute?","r":"Chotto ii?","a":"n_3d7f406c6280.mp3"},{"t":"今日は月曜だよ。","en":"Today is Monday.","r":"Kyō wa getsuyō da yo.","a":"n_6c603916ef4d.mp3"},{"t":"ここに住んでるよ。","en":"I live here.","r":"Koko ni sunderu yo.","a":"n_eb3925bc232d.mp3"},{"t":"すごく具合悪そうだよ。","en":"You're really sick.","r":"Sugoku guai warusō da yo.","a":"n_0da1a908854b.mp3"},{"t":"みんなどこ？","en":"Where is everybody?","r":"Minna doko?","a":"n_ef022c9b474e.mp3"},{"t":"休まなきゃだめだよ。","en":"You have to rest.","r":"Yasumanakya dame da yo.","a":"n_def803114a11.mp3"},{"t":"彼って待てないんだよね。","en":"He doesn't know how to wait.","r":"Kare tte matenai n da yo ne.","a":"n_dc2afe1308eb.mp3"},{"t":"待たなきゃね。","en":"We need to wait.","r":"Matanakya ne.","a":"n_1d62334c2100.mp3"},{"t":"どうかな、様子見よう。","en":"We'll see.","r":"Dō ka na, yōsu miyō.","a":"n_ce7054e98d09.mp3"},{"t":"今日来れる？","en":"Can you come today?","r":"Kyō koreru?","a":"n_d0306eedfcee.mp3"},{"t":"仕事から帰るとこ。","en":"I'm coming from work.","r":"Shigoto kara kaeru toko.","a":"n_93b30a1cc439.mp3"},{"t":"なにか飲む？","en":"Do you want to drink something?","r":"Nanika nomu?","a":"n_51aa45f67c88.mp3"},{"t":"いつも私が払うんだ。","en":"I always pay.","r":"Itsumo watashi ga harau n da.","a":"n_7f77ae7ed9f1.mp3"},{"t":"あとで払うね。","en":"I'll pay you later.","r":"Ato de harau ne.","a":"n_65df6d8c871b.mp3"},{"t":"すごく小さかったよ。","en":"It was very small.","r":"Sugoku chiisakatta yo.","a":"n_565db3226e79.mp3"},{"t":"彼メキシコ出身だよ。","en":"He's from Mexico.","r":"Kare Mekishiko shusshin da yo.","a":"n_744c37c21f91.mp3"},{"t":"いい天気だね。","en":"It's a nice day.","r":"Ii tenki da ne.","a":"n_6220034b3667.mp3"},{"t":"紅茶のほうがいいな。","en":"I prefer tea.","r":"Kōcha no hō ga ii na.","a":"n_a7aabbb53a49.mp3"},{"t":"ここにいてもいい？","en":"Can I stay here?","r":"Koko ni ite mo ii?","a":"n_154482bd5ebb.mp3"},{"t":"ここ知ってる？","en":"Do you know this place?","r":"Koko shitteru?","a":"n_7570afb39d60.mp3"},{"t":"この街知ってるよ。","en":"I know this city.","r":"Kono machi shitteru yo.","a":"n_87d809c9b89e.mp3"},{"t":"今日なにするの？","en":"What are you doing today?","r":"Kyō nani suru no?","a":"n_c2d487953cf3.mp3"},{"t":"どこで言ったの？","en":"Where did you say it?","r":"Doko de itta no?","a":"n_4501fb7a9254.mp3"},{"t":"これすごくおいしい。","en":"It's really good.","r":"Kore sugoku oishii.","a":"n_32522d652538.mp3"},{"t":"君のスマホ見つけたよ。","en":"I found your phone.","r":"Kimi no sumaho mitsuketa yo.","a":"n_12cfac84b8a6.mp3"},{"t":"シャワーさっと済ませるよ。","en":"I shower fast.","r":"Shawā satto sumaseru yo.","a":"n_7d19aebe1ebd.mp3"},{"t":"十ユーロだよ。","en":"It costs ten euros.","r":"Jū yūro da yo.","a":"n_6a2fda322ef8.mp3"},{"t":"昨日いっぱい食べた。","en":"I ate a lot yesterday.","r":"Kinō ippai tabeta.","a":"n_7c954fbec019.mp3"},{"t":"いい人だったよ。","en":"He was a good person.","r":"Ii hito datta yo.","a":"n_095e92a5ba95.mp3"},{"t":"明日でもいい？","en":"Can we do it tomorrow?","r":"Ashita demo ii?","a":"n_a735712b2ef7.mp3"},{"t":"あとで話せるよ。","en":"We can talk afterward.","r":"Ato de hanaseru yo.","a":"n_c02462fccded.mp3"},{"t":"今日なにかする？","en":"Should we do something today?","r":"Kyō nanika suru?","a":"n_9441690d24ee.mp3"},{"t":"パーティーする？","en":"Should we throw a party?","r":"Pātī suru?","a":"n_e0438f33c846.mp3"},{"t":"一緒に運動してるんだ。","en":"We work out together.","r":"Issho ni undō shiteru n da.","a":"n_f96bedc9973f.mp3"},{"t":"スポーツよくやるよ。","en":"I do a lot of sports.","r":"Supōtsu yoku yaru yo.","a":"n_a1f18ed540a2.mp3"},{"t":"どうだったか教えて。","en":"Tell me how it went.","r":"Dō datta ka oshiete.","a":"n_595c713bdb37.mp3"},{"t":"あの犬見て。","en":"Look at that dog.","r":"Ano inu mite.","a":"n_f4021600de3f.mp3"},{"t":"起きたくない。","en":"I don't want to get up.","r":"Okitakunai.","a":"n_9ac801ad9886.mp3"},{"t":"これ試してみる？","en":"Do you want to try this?","r":"Kore tameshite miru?","a":"n_99f4cdaca1f4.mp3"},{"t":"二時だよ。","en":"It's two o'clock.","r":"Ni-ji da yo.","a":"n_b838182d7f78.mp3"},{"t":"名前なんていうの？","en":"What's your name?","r":"Namae nan te iu no?","a":"n_e10456264720.mp3"},{"t":"一緒に来る？","en":"Do you want to come with me?","r":"Issho ni kuru?","a":"n_6181cfb90aaf.mp3"},{"t":"すごく喉かわいた。","en":"I'm really thirsty.","r":"Sugoku nodo kawaita.","a":"n_09d169147dea.mp3"},{"t":"何歳？","en":"How old are you?","r":"Nan-sai?","a":"n_625b2474f75b.mp3"},{"t":"電話するね。","en":"I'm going to call.","r":"Denwa suru ne.","a":"n_c29321958a0e.mp3"}]}