{"lang":"fr","stage":9,"title":"connected, real phrasing","sentences":[{"t":"Je veux rencontrer ta famille.","en":"I want to meet your family.","a":"n_2ca02e8c2bac.mp3"},{"t":"Je me douche et je m'habille.","en":"I shower and get dressed.","a":"n_9887c23e9b15.mp3"},{"t":"Mon frère habite à côté.","en":"My brother lives next door.","a":"n_10c22ac48e5f.mp3"},{"t":"Il est huit heures moins le quart.","en":"It's a quarter to eight.","a":"n_2f64e7261acc.mp3"},{"t":"Celui-là vaut vraiment le coup.","en":"This one is actually worth the money.","a":"n_d780e3bb8e35.mp3"},{"t":"Je vais acheter le ticket.","en":"I'm going to buy the ticket.","a":"n_e731a85d5c7b.mp3"},{"t":"Va tout droit jusqu'à la place.","en":"Go straight until the square.","a":"n_aa289c88acee.mp3"},{"t":"Je l'ai cherché partout.","en":"I looked for it everywhere.","a":"n_f38a6ffbe944.mp3"},{"t":"Je m'inquiète pour mon ami.","en":"I'm worried about my friend.","a":"n_03619e05e22e.mp3"},{"t":"J'ai presque jamais raison.","en":"I'm almost never right.","a":"n_6039fa7b88d2.mp3"},{"t":"Pourquoi t'es si pressé ?","en":"Why are you in such a hurry?","a":"n_d5553de89bcc.mp3"},{"t":"Tu veux sortir ou tu préfères dormir ?","en":"Do you want to go out or would you rather sleep?","a":"n_b04f81f6f470.mp3"},{"t":"Je sais pas me servir de ce téléphone.","en":"I don't know how to use this phone.","a":"n_64b53bed4e1b.mp3"},{"t":"Tu manges chez toi ou dehors ?","en":"Do you eat at home or out?","a":"n_b07f5c03d835.mp3"},{"t":"On a fait une fête vendredi.","en":"We threw a party on Friday.","a":"n_cad8cfee0b39.mp3"},{"t":"Je vais préparer mon sac.","en":"I'm going to pack my bag.","a":"n_e0d77dead5dd.mp3"},{"t":"Me demande pas.","en":"Don't ask me.","a":"n_0c6c7c9aeb93.mp3"},{"t":"J'ai demandé où étaient les toilettes.","en":"I asked where the bathroom was.","a":"n_94a308068d84.mp3"},{"t":"Il m'a demandé quand on se voit.","en":"He asked me when we're meeting up.","a":"n_cf03f8bccf9a.mp3"},{"t":"Elle sait vraiment bien danser.","en":"She knows how to dance really well.","a":"n_1c89eebcaede.mp3"},{"t":"Aujourd'hui c'est le huit mars.","en":"Today is the eighth of March.","a":"n_65d05d2b86d8.mp3"},{"t":"J'ai encore raté le bus.","en":"I missed the bus again.","a":"n_0434fd23889c.mp3"},{"t":"Tu travailles jusqu'à quelle heure aujourd'hui ?","en":"Until what time do you work today?","a":"n_c223ecde9920.mp3"},{"t":"Il se couche super tard.","en":"He goes to bed really late.","a":"n_3096390c6ae3.mp3"},{"t":"Elle mange et après elle bosse.","en":"She eats and then works.","a":"n_4cfb12b46974.mp3"},{"t":"On mange à la maison tous les jours.","en":"We eat at home every day.","a":"n_caa892cdf5c4.mp3"},{"t":"Je voulais essayer un truc nouveau aujourd'hui.","en":"I wanted to try something new today.","a":"n_9fdf809c9e7e.mp3"},{"t":"Prends ce cachet et repose-toi.","en":"Take this pill and rest.","a":"n_4fecc9024ad4.mp3"},{"t":"Il fait très chaud l'été.","en":"It's really hot in summer.","a":"n_0473e1837625.mp3"},{"t":"On se voit demain ou jeudi ?","en":"Shall we meet tomorrow or Thursday?","a":"n_d33a609fa575.mp3"},{"t":"T'as un truc contre la douleur ?","en":"Do you have something for the pain?","a":"n_04cfd7a55d87.mp3"},{"t":"Je le vends cent euros.","en":"I'm selling it for a hundred euros.","a":"n_34cfe26d28a1.mp3"},{"t":"Des fois j'ai envie d'un truc sucré.","en":"Sometimes I want something sweet.","a":"n_bbf1b3187e32.mp3"},{"t":"Tu vas venir me voir ?","en":"Are you going to come see me?","a":"n_0e9906240fe4.mp3"},{"t":"Tu rentres de voyage quand ?","en":"When do you get back from your trip?","a":"n_d3ad41f686e8.mp3"},{"t":"Je fais les courses le samedi.","en":"I do the shopping on Saturdays.","a":"n_962361edaebe.mp3"},{"t":"Dis-moi ce que le chef a dit.","en":"Tell me what the boss said.","a":"n_77ef6d836cf5.mp3"},{"t":"Il m'a pas dit quand il rentrait.","en":"He didn't tell me when he was coming back.","a":"n_f5d641426553.mp3"},{"t":"Pourquoi t'as pas demandé avant ?","en":"Why didn't you ask earlier?","a":"n_2fa8a404cf05.mp3"},{"t":"Dis-moi pourquoi tu rigolais.","en":"Tell me why you were laughing.","a":"n_2bb4807cf92c.mp3"},{"t":"Mon frère sait tout réparer.","en":"My brother knows how to fix everything.","a":"n_986542f3f37f.mp3"},{"t":"Marco sait parler plein de langues.","en":"Marco knows how to speak many languages.","a":"n_81a6dce95eb4.mp3"},{"t":"Je connais pas cette fille.","en":"I don't know that girl.","a":"n_67eaa7e9a211.mp3"},{"t":"Regarde bien avant de traverser.","en":"Look carefully before you cross.","a":"n_9f270bdb566c.mp3"},{"t":"Je trouve pas mon autre chaussure.","en":"I can't find my other shoe.","a":"n_913e1aecc1c7.mp3"},{"t":"Je me lève à sept heures.","en":"I get up at seven.","a":"n_7884b5fb8c0e.mp3"},{"t":"Je me couche à onze heures.","en":"I go to bed at eleven.","a":"n_29c288ca845e.mp3"},{"t":"Tu te lèves à quelle heure ?","en":"What time do you get up?","a":"n_06f5b93b63f0.mp3"},{"t":"Tu habites ici depuis combien de temps ?","en":"How long have you been living here?","a":"n_7b06e80723e9.mp3"},{"t":"Tu finis à quelle heure aujourd'hui ?","en":"What time do you finish today?","a":"n_0943e8148c5f.mp3"},{"t":"Mon anniversaire est en mai.","en":"My birthday is in May.","a":"n_86072c5f6067.mp3"},{"t":"Chaque lundi je recommence.","en":"Every Monday I start again.","a":"n_95429eee1bfb.mp3"},{"t":"L'eau coûte un euro.","en":"The water costs one euro.","a":"n_fc673b5fca0c.mp3"},{"t":"T'as payé combien ton téléphone ?","en":"How much did you pay for your phone?","a":"n_6e2f1fa04dba.mp3"},{"t":"Je dépense plein d'argent en café.","en":"I spend a lot of money on coffee.","a":"n_f8c63df52ddb.mp3"},{"t":"J'ai mal partout.","en":"My whole body hurts.","a":"n_72a764ca0d20.mp3"},{"t":"Demain j'irai mieux.","en":"Tomorrow I'll feel better.","a":"n_dc0a48e4594c.mp3"},{"t":"J'étudie l'espagnol tous les matins.","en":"I study Spanish every morning.","a":"n_36417ee530a1.mp3"},{"t":"Il est trois heures et demie.","en":"It's three thirty.","a":"n_9740a9300a0f.mp3"},{"t":"Mon père a cinquante ans.","en":"My dad is fifty years old.","a":"n_fc1557dc1cee.mp3"},{"t":"On devrait sortir plus souvent.","en":"We should go out more often.","a":"n_0ad500f78f2d.mp3"},{"t":"Me dis pas la fin.","en":"Don't tell me the ending.","a":"n_48e8908a6520.mp3"},{"t":"On paie chacun pour soi ?","en":"Should we each pay our own?","a":"n_bfb73937aca6.mp3"},{"t":"Avant je vivais chez mes parents.","en":"I used to live with my parents.","a":"n_70c9151227e0.mp3"},{"t":"Je veux vendre ces vieux trucs.","en":"I want to sell these old things.","a":"n_262bbe74b407.mp3"},{"t":"Ce film m'a fait pleurer.","en":"That movie made me cry.","a":"n_5b584aca5b1e.mp3"},{"t":"J'ai plein de trucs à faire aujourd'hui.","en":"I have a lot to do today.","a":"n_0423deb65548.mp3"},{"t":"Demain j'ai plein de trucs à faire.","en":"Tomorrow I have a lot to do.","a":"n_888d76e8322c.mp3"},{"t":"Je sais juste qu'il est tard.","en":"I only know that it's late.","a":"n_b71a25a91723.mp3"},{"t":"Qui dit que je peux pas ?","en":"Who says I can't?","a":"n_bf5e109319d9.mp3"},{"t":"J'ai tout ce qu'il me faut.","en":"I have everything I need.","a":"n_7241c3c7397b.mp3"},{"t":"Elle dit qu'elle sait pas.","en":"She says she doesn't know.","a":"n_6a9d9c3565cc.mp3"},{"t":"Je peux pas là, désolé.","en":"I can't right now, sorry.","a":"n_1863d7985c31.mp3"},{"t":"Je mange jamais avant de travailler.","en":"I never eat before working.","a":"n_0477504dc5c0.mp3"},{"t":"Je dois aller chez le médecin.","en":"I have to go to the doctor.","a":"n_1384c528460f.mp3"},{"t":"J'y suis pas allé parce que j'étais crevé.","en":"I didn't go because I was tired.","a":"n_d842d8c7857e.mp3"},{"t":"Non, je suis pas encore prêt.","en":"No, I'm not ready yet.","a":"n_453062f31d27.mp3"},{"t":"Je suis toujours en retard, je sais.","en":"I'm always late, I know.","a":"n_76d525cc3911.mp3"},{"t":"Je veux rien d'autre, merci.","en":"I don't want anything else, thanks.","a":"n_5ebc94a05c0a.mp3"},{"t":"Ça va, merci. Et toi ?","en":"I'm good, thanks. And you?","a":"n_f836fe89b94f.mp3"},{"t":"Je suis triste parce que je suis seul.","en":"I'm sad because I'm alone.","a":"n_01a5d8d72023.mp3"},{"t":"Je veux la même chose que toi.","en":"I want the same thing as you.","a":"n_5dc1877a6df4.mp3"},{"t":"Je sais pas dire non.","en":"I don't know how to say no.","a":"n_c10c4d63d36c.mp3"},{"t":"Pardon, il est où le bus ?","en":"Excuse me, where's the bus?","a":"n_bb9619c30c8c.mp3"},{"t":"Désolé, j'ai cinq minutes de retard.","en":"Sorry, I'm five minutes late.","a":"n_4b94d684734b.mp3"},{"t":"Elle s'appelle Ana, c'est ça ?","en":"Her name is Ana, right?","a":"n_dae8ecfb554e.mp3"},{"t":"J'ai sommeil, il me faut un café.","en":"I'm sleepy, I need a coffee.","a":"n_9f7781c88033.mp3"},{"t":"Je suis pas malade, juste fatigué.","en":"I'm not sick, I'm just tired.","a":"n_32e4df7a3e8b.mp3"},{"t":"J'ai besoin de me reposer un peu.","en":"I need to rest a bit.","a":"n_c03daebf8ebd.mp3"},{"t":"Dis-moi la vérité, s'il te plaît.","en":"Tell me the truth, please.","a":"n_53a6ad2f47a1.mp3"},{"t":"Je suis content parce que c'est vendredi.","en":"I'm happy because it's Friday.","a":"n_194d5a5fe1b7.mp3"},{"t":"Parce que je préfère toujours le thé.","en":"Because I always prefer tea.","a":"n_f8ae57626cb6.mp3"},{"t":"Tu peux manger ce que tu veux.","en":"You can eat whatever you want.","a":"n_e7798a3605d1.mp3"},{"t":"Je trouve ça vraiment bon.","en":"I think it's really good.","a":"n_81d455868afe.mp3"}]}