{"lang":"fr","stage":1,"title":"tiny everyday sentences (1–4 words, no clauses)","sentences":[{"t":"Je peux.","en":"I can.","a":"n_cfc99e2e7e9d.mp3"},{"t":"Je peux ?","en":"Can I?","a":"n_ab0fb090384c.mp3"},{"t":"On y va.","en":"Let's go.","a":"n_78745ff6ca7d.mp3"},{"t":"Tu sais ?","en":"You know?","a":"n_172151b99cb0.mp3"},{"t":"Tu viens ?","en":"Are you coming?","a":"n_52269b6fa6d4.mp3"},{"t":"Salut.","en":"Hi.","a":"n_c0e0826f4faa.mp3"},{"t":"Enchanté.","en":"Nice to meet you.","a":"n_0dc0d2bd5486.mp3"},{"t":"Enchantée.","en":"Nice to meet you.","a":"n_5187e869db01.mp3"},{"t":"Regarde-moi.","en":"Look at me.","a":"n_2c129052927b.mp3"},{"t":"Salut.","en":"Bye.","a":"n_c0e0826f4faa.mp3"},{"t":"J'en veux plus.","en":"I want more.","a":"n_7f147c760d4f.mp3"},{"t":"Je sais pas.","en":"I don't know.","a":"n_78fbe6253195.mp3"},{"t":"J'y vais pas.","en":"I'm not going.","a":"n_d1a6d465175d.mp3"},{"t":"J'aime bien.","en":"I like it.","a":"n_99d612d05cf9.mp3"},{"t":"Tu aimes ?","en":"Do you like it?","a":"n_6c9e83fdb1ce.mp3"},{"t":"C'est elle.","en":"It's her.","a":"n_f9c83005cf11.mp3"},{"t":"Ça va.","en":"I'm good.","a":"n_ad2799025ff1.mp3"},{"t":"Je peux pas.","en":"I can't.","a":"n_4162f108d0d6.mp3"},{"t":"Autre chose ?","en":"Anything else?","a":"n_78920456b488.mp3"},{"t":"Je veux un café.","en":"I want coffee.","a":"n_67368f7b24b9.mp3"},{"t":"Je sais.","en":"I know.","a":"n_eb7439c8f2f8.mp3"},{"t":"J'y vais demain.","en":"I'm going tomorrow.","a":"n_9586a5dda225.mp3"},{"t":"Je veux manger.","en":"I want to eat.","a":"n_b0bc3654a59a.mp3"},{"t":"Je sais déjà.","en":"I already know.","a":"n_5b66fe4be519.mp3"},{"t":"J'arrive.","en":"I'm coming.","a":"n_0b7c2868a2aa.mp3"},{"t":"Ça fait mal.","en":"It hurts.","a":"n_97a4c49a0638.mp3"},{"t":"Ça fait mal ?","en":"Does it hurt?","a":"n_c52130667acb.mp3"},{"t":"C'est moi.","en":"It's me.","a":"n_c31ce3af2d72.mp3"},{"t":"Je suis Marco.","en":"I'm Marco.","a":"n_2771904e43c4.mp3"},{"t":"Je suis crevé.","en":"I'm tired.","a":"n_3e38607097f7.mp3"},{"t":"Je fais du café.","en":"I'm making coffee.","a":"n_39c43ae99d9d.mp3"},{"t":"Je mange beaucoup.","en":"I eat a lot.","a":"n_73c77d8ffe2d.mp3"},{"t":"Je veux dormir.","en":"I want to sleep.","a":"n_714ce2f945c3.mp3"},{"t":"C'est lui.","en":"It's him.","a":"n_883936430b9a.mp3"},{"t":"C'est qui ?","en":"Who is it?","a":"n_bf3704ece14e.mp3"},{"t":"Je suis espagnol.","en":"I'm Spanish.","a":"n_428a922a9d8e.mp3"},{"t":"Tu peux.","en":"You can.","a":"n_a73d452f9f9c.mp3"},{"t":"Tu en veux plus ?","en":"Do you want more?","a":"n_4033d4736452.mp3"},{"t":"Tu veux un café ?","en":"Do you want coffee?","a":"n_cd0bb065a0b3.mp3"},{"t":"Tu veux sortir ?","en":"Do you want to go out?","a":"n_2f27d50e7a9d.mp3"},{"t":"J'apprends l'espagnol.","en":"I study Spanish.","a":"n_333472e3a060.mp3"},{"t":"C'est combien ?","en":"How much is it?","a":"n_0e9bad1f076f.mp3"},{"t":"Ça coûte combien ?","en":"How much is it?","a":"n_bf5b961ef6ca.mp3"},{"t":"Qui sait ?","en":"Who knows?","a":"n_0c3136eaa06f.mp3"},{"t":"C'est toi.","en":"It's you.","a":"n_2e72732b8d56.mp3"},{"t":"C'est toi ?","en":"Is that you?","a":"n_2268679586c5.mp3"},{"t":"T'es qui ?","en":"Who are you?","a":"n_372fcc97beeb.mp3"},{"t":"T'es espagnol ?","en":"Are you Spanish?","a":"n_39b2cda7dc7d.mp3"},{"t":"J'ai froid.","en":"I'm cold.","a":"n_b69a2ffba1b0.mp3"},{"t":"T'as froid ?","en":"Are you cold?","a":"n_c22f97f016f9.mp3"},{"t":"Il fait froid.","en":"It's cold.","a":"n_456c4aad09f0.mp3"},{"t":"Regarde par ici.","en":"Look over here.","a":"n_1ee3a3db62c3.mp3"},{"t":"Regarde ça.","en":"Look at this.","a":"n_298f357c9b34.mp3"},{"t":"Je suis content.","en":"I'm happy.","a":"n_756c4aa567d9.mp3"},{"t":"Ça va ?","en":"Are you okay?","a":"n_a0b5e690b2f0.mp3"},{"t":"Comment ça va ?","en":"How are you?","a":"n_0b1616040c4b.mp3"},{"t":"Ça va pas.","en":"I'm not doing well.","a":"n_9ea06bf43589.mp3"},{"t":"J'ai faim.","en":"I'm hungry.","a":"n_0b3d1e73af35.mp3"},{"t":"T'as faim ?","en":"Are you hungry?","a":"n_528d613f3659.mp3"},{"t":"Je te vois.","en":"I see you.","a":"n_2f9b82270c6e.mp3"},{"t":"Je me lève.","en":"I get up.","a":"n_37018bcbab8e.mp3"},{"t":"Je suis Ana.","en":"I'm Ana.","a":"n_93bffe7a5253.mp3"},{"t":"Je suis prêt.","en":"I'm ready.","a":"n_469e40d05d83.mp3"},{"t":"T'as raison.","en":"You're right.","a":"n_1d7f0c01ef24.mp3"},{"t":"Je veux de l'eau.","en":"I want water.","a":"n_9cc2bdb96ed3.mp3"},{"t":"J'ai besoin d'eau.","en":"I need water.","a":"n_420cd0708ca2.mp3"},{"t":"On va bien.","en":"We're good.","a":"n_9ac4dbdb90a5.mp3"},{"t":"C'est pas cher.","en":"It's cheap.","a":"n_4db0a5569e1a.mp3"},{"t":"Je suis occupé.","en":"I'm busy.","a":"n_bcc6b08443b9.mp3"},{"t":"Je viens avec toi.","en":"I'm going with you.","a":"n_a4a3d7c0623a.mp3"},{"t":"J'adore.","en":"I love it.","a":"n_3c57f35f042c.mp3"},{"t":"Je suis en retard.","en":"I'm late.","a":"n_c47ba400c35f.mp3"},{"t":"Tu viens quand ?","en":"When are you coming?","a":"n_6b809992965c.mp3"},{"t":"Je suis triste.","en":"I'm sad.","a":"n_ce24398ab8bb.mp3"},{"t":"Il fait chaud.","en":"It's hot.","a":"n_60df36ad8664.mp3"},{"t":"Je préfère l'eau.","en":"I prefer water.","a":"n_988a6908148f.mp3"},{"t":"Je fais du sport.","en":"I work out.","a":"n_f13f05face75.mp3"},{"t":"J'ai sommeil.","en":"I'm sleepy.","a":"n_783f9a5e2788.mp3"},{"t":"T'as besoin de quelque chose ?","en":"Do you need anything?","a":"n_1792c973a83d.mp3"},{"t":"Je vis seul.","en":"I live alone.","a":"n_a083549e2266.mp3"},{"t":"Je suis malade.","en":"I'm sick.","a":"n_94918b7c0ab2.mp3"},{"t":"J'arrive demain.","en":"I'm coming tomorrow.","a":"n_d6e785b10aaa.mp3"},{"t":"Je reviens tout de suite.","en":"I'll be right back.","a":"n_3e4b4ddba62f.mp3"},{"t":"Je reviens vite.","en":"I'll be right back.","a":"n_a645c97ddbb5.mp3"},{"t":"Raconte-moi tout.","en":"Tell me everything.","a":"n_6371e6fe15fa.mp3"},{"t":"Je veux te voir.","en":"I want to see you.","a":"n_6915eec0f30b.mp3"},{"t":"Je suis pressé.","en":"I'm in a hurry.","a":"n_07bdbf691230.mp3"},{"t":"Tu fais quoi ?","en":"What are you doing?","a":"n_5d26df5d0475.mp3"},{"t":"Donne-moi ça.","en":"Give me that.","a":"n_b5240034b0b1.mp3"},{"t":"Je l'ai trouvé.","en":"I found it.","a":"n_e5e2c3e9eb21.mp3"},{"t":"Je dors peu.","en":"I don't sleep much.","a":"n_358ded44c56c.mp3"},{"t":"Je dors bien.","en":"I sleep well.","a":"n_805c7203d9eb.mp3"},{"t":"Continue tout droit.","en":"Keep going straight.","a":"n_401b32bd16f6.mp3"},{"t":"Je suis crevée.","en":"I'm tired.","a":"n_2832856c33a5.mp3"}]}